contrat/__init__.py
contrat/tests/sample.py
contrat/tests/test_contract.py
contrat-0.3.0.dist-info/AUTHORS
contrat-0.3.0.dist-info/LICENSE
contrat-0.3.0.dist-info/METADATA
contrat-0.3.0.dist-info/WHEEL
contrat-0.3.0.dist-info/pbr.json
contrat-0.3.0.dist-info/top_level.txt
contrat-0.3.0.dist-info/RECORD
