Metadata-Version: 2.1
Name: contrat
Version: 0.3.0
Summary: Python module to keep function signature introspection compatibility between python version
Home-page: https://github.com/4383/contrat/
Author: Hervé Beraud
Author-email: herveberaud.pro@gmail.com
License: MIT
Platform: UNKNOWN
Classifier: Development Status :: 3 - Alpha
Classifier: Intended Audience :: Information Technology
Classifier: License :: OSI Approved :: MIT License
Classifier: Operating System :: POSIX
Classifier: Programming Language :: Python
Classifier: Programming Language :: Python :: 3
Classifier: Programming Language :: Python :: 2.7
Classifier: Programming Language :: Python :: 3
Classifier: Programming Language :: Python :: 3.5
Classifier: Programming Language :: Python :: 3.6
Classifier: Programming Language :: Python :: 3.7
Provides-Extra: tests
Requires-Dist: tox ; extra == 'tests'
